ixbrowser_local_api/__init__.py
ixbrowser_local_api/client.py
ixbrowser_local_api/consts.py
ixbrowser_local_api/entities.py
ixbrowser_local_api/errors.py
ixbrowser_local_api/utils.py
ixbrowser_local_api/version.py
ixbrowser_local_api-1.2.2.dist-info/licenses/LICENSE
ixbrowser_local_api-1.2.2.dist-info/METADATA
ixbrowser_local_api-1.2.2.dist-info/WHEEL
ixbrowser_local_api-1.2.2.dist-info/top_level.txt
ixbrowser_local_api-1.2.2.dist-info/RECORD
